{"pageProps":{"product":{"__typename":"Product","id":"clk7d5xv00bgq0bk1p4s9991t","name":"SSAL 2000™ Fry Pan 10\" ","price":840.25,"slug":"ssal-2000tm-fry-pan-10","description":{"__typename":"RichText","html":"<ul><li><div>Case of 6 each</div></li><li><div><li><div>Finest 18-8 stainless interior is permanently bonded to hard aluminum<br> body to create the ultimate fry pan for any foodservice environment</div></li></div><div><li><div>Aluminum body ensures maximum heat transfer throughout the pan; eliminates hot spots and scorching</div></li></div><div><li><div>Special rivet design securely attaches handle to pan; bond will not loosen like traditional rivets</div></li></div></li></ul><p></p>"},"image":{"__typename":"Asset","url":"https://media.graphassets.com/bzB2KYeBQ2PaxLkCMShh"}}},"__N_SSG":true}